astropixel/__init__.py
astropixel/catalog_querry.py
astropixel/cutout.py
astropixel/make_star.py
astropixel/plot_stars.py
AstroPixel-1.0.2.dist-info/LICENSE
AstroPixel-1.0.2.dist-info/METADATA
AstroPixel-1.0.2.dist-info/WHEEL
AstroPixel-1.0.2.dist-info/top_level.txt
AstroPixel-1.0.2.dist-info/RECORD
