Metadata-Version: 2.1
Name: AstroPixel
Version: 1.0.2
Summary: AstroPixel project made for CodeAstro!
Author-email: Savannah Gramze <savannahgramze@ufl.edu>, S M Rafee Adnan <smrafee.adnan@louisville.edu>
License: MIT License
Keywords: codeastro,astropixel,pixel art,pixelart,astronomy,star map
License-File: LICENSE
Requires-Dist: astropy >=4.3.0
Requires-Dist: numpy >=1.21.0
Requires-Dist: matplotlib >=3.4.2
Requires-Dist: spectral-cube >=0.6.5
Requires-Dist: regions >=0.9
Requires-Dist: astroquery >=0.4.7
Requires-Dist: pytest >=8.2.2
